disconv.py
disconv-0.0.3.dist-info/LICENSE.txt
disconv-0.0.3.dist-info/METADATA
disconv-0.0.3.dist-info/WHEEL
disconv-0.0.3.dist-info/top_level.txt
disconv-0.0.3.dist-info/RECORD
